{
  "dailynet-2023-02-01": {
    "aliases": [],
    "category": "Periodic Teztnets",
    "chain_name": "TEZOS-DAILYNET-2023-02-01T00:00:00.000Z",
    "description": "A testnet that restarts every day launched from tezos/tezos master branch and protocol alpha.",
    "docker_build": "tezos/tezos:master_025bec8c_20230131181542",
    "faucet_url": "https://faucet.dailynet-2023-02-01.teztnets.xyz",
    "git_ref": "025bec8c",
    "human_name": "Dailynet",
    "indexers": [],
    "last_baking_daemon": "alpha",
    "masked_from_main_page": false,
    "network_url": "https://teztnets.xyz/dailynet-2023-02-01",
    "protocols": [
      {
        "level": 0,
        "replacement_protocol": "ProtoALphaALphaALphaALphaALphaALphaALphaALphaDdp3zK"
      }
    ],
    "rpc_url": "https://rpc.dailynet-2023-02-01.teztnets.xyz",
    "activated_on": "2023-02-01"
  },
  "ghostnet": {
    "aliases": [
      "ithacanet"
    ],
    "category": "Long-running Teztnets",
    "chain_name": "TEZOS_ITHACANET_2022-01-25T15:00:00Z",
    "description": "Ghostnet is the long-running testnet for Tezos.",
    "docker_build": "tezos/tezos:v15.1",
    "faucet_url": "https://faucet.ghostnet.teztnets.xyz",
    "git_ref": "v15.1",
    "human_name": "Ghostnet",
    "indexers": [
      {
        "name": "TzKT",
        "url": "https://ghostnet.tzkt.io"
      },
      {
        "name": "TzStats",
        "url": "https://ghost.tzstats.com"
      }
    ],
    "last_baking_daemon": "PtLimaPt",
    "masked_from_main_page": false,
    "network_url": "https://teztnets.xyz/ghostnet",
    "protocols": [
      {
        "level": 0,
        "replacement_protocol": "PtHangz2aRngywmSRGGvrcTyMbbdpWdpFKuS4uMWxg2RaH9i1qx"
      },
      {
        "level": 8191,
        "replacement_protocol": "Psithaca2MLRFYargivpo7YvUr7wUDqyxrdhC5CQq78mRvimz6A"
      },
      {
        "level": 765952,
        "replacement_protocol": "PtJakart2xVj7pYXJBXrqHgd82rdkLey5ZeeGwDgPp9rhQUbSqY"
      },
      {
        "level": 1191936,
        "replacement_protocol": "PtKathmankSpLLDALzWw7CGD2j2MtyveTwboEYokqUCP4a1LxMg"
      },
      {
        "level": 1654784,
        "replacement_protocol": "PtLimaPtLMwfNinJi9rCfDPWea8dFgTZ1MeJ9f1m2SRic6ayiwW"
      }
    ],
    "rpc_url": "https://rpc.ghostnet.teztnets.xyz",
    "activated_on": "2022-01-25"
  },
  "limanet": {
    "aliases": [],
    "category": "Protocol Teztnets",
    "chain_name": "TEZOS_LIMANET_2022-10-13T15:00:00Z",
    "description": "Test Chain for the Lima Protocol Proposal",
    "docker_build": "tezos/tezos:v15.1",
    "faucet_url": "https://faucet.limanet.teztnets.xyz",
    "git_ref": "v15.1",
    "human_name": "Limanet",
    "indexers": [
      {
        "name": "TzKT",
        "url": "https://limanet.tzkt.io"
      }
    ],
    "last_baking_daemon": "PtLimaPt",
    "masked_from_main_page": false,
    "network_url": "https://teztnets.xyz/limanet",
    "protocols": [
      {
        "level": 0,
        "replacement_protocol": "PtKathmankSpLLDALzWw7CGD2j2MtyveTwboEYokqUCP4a1LxMg"
      },
      {
        "level": 8192,
        "replacement_protocol": "PtLimaPtLMwfNinJi9rCfDPWea8dFgTZ1MeJ9f1m2SRic6ayiwW"
      }
    ],
    "rpc_url": "https://rpc.limanet.teztnets.xyz",
    "activated_on": "2022-10-13"
  },
  "mondaynet-2023-01-30": {
    "aliases": [],
    "category": "Periodic Teztnets",
    "chain_name": "TEZOS-MONDAYNET-2023-01-30T00:00:00.000Z",
    "description": "A testnet that restarts every Monday launched from tezos/tezos master branch. It runs Lima with SCORU and ZK feature flags on for 8 cycles then upgrades to proto Alpha.",
    "docker_build": "tezos/tezos:master_68779c31_20230129203845",
    "faucet_url": "https://faucet.mondaynet-2023-01-30.teztnets.xyz",
    "git_ref": "68779c31",
    "human_name": "Mondaynet",
    "indexers": [],
    "last_baking_daemon": "alpha",
    "masked_from_main_page": false,
    "network_url": "https://teztnets.xyz/mondaynet-2023-01-30",
    "protocols": [
      {
        "level": 0,
        "replacement_protocol": "PtLimaPtLMwfNinJi9rCfDPWea8dFgTZ1MeJ9f1m2SRic6ayiwW"
      },
      {
        "level": 512,
        "replacement_protocol": "ProtoALphaALphaALphaALphaALphaALphaALphaALphaDdp3zK"
      }
    ],
    "rpc_url": "https://rpc.mondaynet-2023-01-30.teztnets.xyz",
    "activated_on": "2023-01-30"
  },
  "mumbainet": {
    "aliases": [],
    "category": "Protocol Teztnets",
    "chain_name": "TEZOS_MUMBAINET_2023-01-19T15:00:00Z",
    "description": "Test Chain for the Mumbai Protocol Proposal",
    "docker_build": "tezos/tezos:v16.0-rc1",
    "faucet_url": "https://faucet.mumbainet.teztnets.xyz",
    "git_ref": "v16.0-rc1",
    "human_name": "Mumbainet",
    "indexers": [],
    "last_baking_daemon": "PtMumbai",
    "masked_from_main_page": false,
    "network_url": "https://teztnets.xyz/mumbainet",
    "protocols": [
      {
        "level": 0,
        "replacement_protocol": "PtLimaPtLMwfNinJi9rCfDPWea8dFgTZ1MeJ9f1m2SRic6ayiwW"
      }
    ],
    "rpc_url": "https://rpc.mumbainet.teztnets.xyz",
    "activated_on": "2023-01-19"
  }
}
